odoo/addons/web_search_date/README.rst
odoo/addons/web_search_date/__init__.py
odoo/addons/web_search_date/__manifest__.py
odoo/addons/web_search_date/i18n/web_search_date.pot
odoo/addons/web_search_date/readme/CONTRIBUTORS.rst
odoo/addons/web_search_date/readme/DESCRIPTION.rst
odoo/addons/web_search_date/readme/USAGE.rst
odoo/addons/web_search_date/static/description/icon.png
odoo/addons/web_search_date/static/description/index.html
odoo/addons/web_search_date/static/src/js/widget.js
odoo/addons/web_search_date/views/web_widget_image_url.xml
odoo11_addon_web_search_date-11.0.1.0.0.99.dev3.dist-info/METADATA
odoo11_addon_web_search_date-11.0.1.0.0.99.dev3.dist-info/WHEEL
odoo11_addon_web_search_date-11.0.1.0.0.99.dev3.dist-info/top_level.txt
odoo11_addon_web_search_date-11.0.1.0.0.99.dev3.dist-info/RECORD
